booking/__init__.py
booking/__main__.py
booking/download_hotels.py
booking/download_test_data.py
booking/api/__init__.py
booking/api/booking_api.py
booking/api/exceptions.py
omim_booking-10.3.0rc2.dist-info/METADATA
omim_booking-10.3.0rc2.dist-info/WHEEL
omim_booking-10.3.0rc2.dist-info/top_level.txt
omim_booking-10.3.0rc2.dist-info/RECORD
