Metadata-Version: 2.1
Name: omim-booking
Version: 10.3.0rc2
Summary: This package is a library for dealing with booking.com.
Home-page: https://github.com/mapsme
Author: My.com B.V. (Mail.Ru Group)
Author-email: dev@maps.me
License: UNKNOWN
Platform: UNKNOWN
Classifier: Programming Language :: Python :: 3
Classifier: License :: OSI Approved :: Apache Software License
Requires-Python: >=3.6
Requires-Dist: eviltransform (==0.1.1)
Requires-Dist: ratelimit (==2.2.1)
Requires-Dist: requests (==2.23.0)
Requires-Dist: tqdm (==4.32.2)
